Workbook

Sheet Raw_Financials
B2: Line Item | C2: FY2015 | D2: FY2016 | E2: FY2017 | F2: FY2018 | G2: FY2019 | H2: FY2020 | I2: FY2021 | J2: FY2022 | K2: FY2023 | L2: FY2024
B3: Net Operating Revenues | C3: 44294 | D3: 41836 | E3: 36212 | F3: 34300 | G3: 37266 | H3: 33014 | I3: 38655 | J3: 43004 | K3: 45754 | L3: 47061
B4: COGS | C4: 17482 | D4: 16465 | E4: 13721 | F4: 13067 | G4: 14619 | H4: 13433 | I4: 15357 | J4: 18000 | K4: 18520 | L4: 18324
B5: Gross Profit | C5: 26812 | D5: 25398 | E5: 22491 | F5: 21233 | G5: 22647 | H5: 19581 | I5: 23298 | J5: 25004 | K5: 27234 | L5: 28737
B6: SG&A Expenses | C6: 16427 | D6: 15370 | E6: 12834 | F6: 11002 | G6: 12013 | H6: 9731 | I6: 12144 | J6: 12880 | K6: 13972 | L6: 14582
B7: Other Operating Charges | C7: 1657 | D7: 1371 | E7: 1902 | F7: 1079 | G7: 458 | H7: 853 | I7: 846 | J7: 1215 | K7: 1951 | L7: 4163
B8: Operating Income (EBIT) | C8: 8728 | D8: 8657 | E8: 7755 | F8: 9152 | G8: 10086 | H8: 8997 | I8: 10308 | J8: 10909 | K8: 11311 | L8: 9992
C12: 2015 | D12: 2016 | E12: 2017 | F12: 2018 | G12: 2019 | H12: 2020 | I12: 2021 | J12: 2022 | K12: 2023 | L12: 2024
B13: Revenue Growth in % | D13: =(Raw_Financials!D3/Raw_Financials!C3)-1 -> -0.055492843 | E13: =(Raw_Financials!E3/Raw_Financials!D3)-1 -> -0.13442968 | F13: =(Raw_Financials!F3/Raw_Financials!E3)-1 -> -0.052800177 | G13: =(Raw_Financials!G3/Raw_Financials!F3)-1 -> 0.086472303 | H13: =(Raw_Financials!H3/Raw_Financials!G3)-1 -> -0.11409864 | I13: =(Raw_Financials!I3/Raw_Financials!H3)-1 -> 0.1708669 | J13: =(Raw_Financials!J3/Raw_Financials!I3)-1 -> 0.11250808 | K13: =(Raw_Financials!K3/Raw_Financials!J3)-1 -> 0.06394754 | L13: =(Raw_Financials!L3/Raw_Financials!K3)-1 -> 0.028565808
C46: 2015 | D46: 2016 | E46: 2017 | F46: 2018 | G46: 2019 | H46: 2020 | I46: 2021 | J46: 2022 | K46: 2023 | L46: 2024
B47: Gross Margin % | C47: =C5/C3 -> 0.605319 | D47: =D5/D3 -> 0.60708481 | E47: =E5/E3 -> 0.62109246 | F47: =F5/F3 -> 0.6190379 | G47: =G5/G3 -> 0.60771212 | H47: =H5/H3 -> 0.59311201 | I47: =I5/I3 -> 0.60271634 | J47: =J5/J3 -> 0.58143429 | ... L47: =L5/L3 -> 0.61063301
C78: 2015 | D78: 2016 | E78: 2017 | F78: 2018 | G78: 2019 | H78: 2020 | I78: 2021 | J78: 2022 | K78: 2023 | L78: 2024
B79: SG&A as % of Revenue | C79: =C6/C3 -> 0.37086287 | D79: =D6/D3 -> 0.36738694 | E79: =E6/E3 -> 0.3544129 | F79: =F6/F3 -> 0.32075802 | G79: =G6/G3 -> 0.32235818 | H79: =H6/H3 -> 0.29475374 | I79: =I6/I3 -> 0.31416376 | J79: =J6/J3 -> 0.29950702 | ... L79: =L6/L3 -> 0.30985317
B80: Change in SG&A Expense | D80: =(D6/C6)-1 -> -0.064345285 | E80: =(E6/D6)-1 -> -0.16499675 | F80: =(F6/E6)-1 -> -0.14274583 | G80: =(G6/F6)-1 -> 0.091892383 | H80: =(H6/G6)-1 -> -0.18996088 | I80: =(I6/H6)-1 -> 0.2479704 | J80: =(J6/I6)-1 -> 0.060606061 | K80: =(K6/J6)-1 -> 0.084782609 | L80: =(L6/K6)-1 -> 0.043658746
C112: 2015 | D112: 2016 | E112: 2017 | F112: 2018 | G112: 2019 | H112: 2020 | I112: 2021 | J112: 2022 | K112: 2023 | L112: 2024
B113: EBIT Margin % | C113: =C8/C3 -> 0.197047 | D113: =D8/D3 -> 0.20692705 | E113: =E8/E3 -> 0.21415553 | F113: =F8/F3 -> 0.26682216 | G113: =G8/G3 -> 0.27064885 | H113: =H8/H3 -> 0.27252075 | I113: =I8/I3 -> 0.26666667 | J113: =J8/J3 -> 0.25367408 | ... L113: =L8/L3 -> 0.21232018
